oda_integral_wrapper/__init__.py
oda_integral_wrapper/catalog.py
oda_integral_wrapper/common_nb_tools.py
oda_integral_wrapper/fit_cyclotron.py
oda_integral_wrapper/fitimage.py
oda_integral_wrapper/get_osa10_11_factor.py
oda_integral_wrapper/helper_functions.py
oda_integral_wrapper/itime.py
oda_integral_wrapper/oda_structures.py
oda_integral_wrapper/planning.py
oda_integral_wrapper/wrapper.py
oda_integral_wrapper-1.5.18.dist-info/LICENSE.rst
oda_integral_wrapper-1.5.18.dist-info/METADATA
oda_integral_wrapper-1.5.18.dist-info/WHEEL
oda_integral_wrapper-1.5.18.dist-info/entry_points.txt
oda_integral_wrapper-1.5.18.dist-info/top_level.txt
oda_integral_wrapper-1.5.18.dist-info/RECORD
