Metadata-Version: 2.1
Name: oda_integral_wrapper
Version: 1.5.18
Summary: wrapper for INTEGRAL analysis using the API plugin for Multi-messenger online data analysis
Home-page: https://gitlab.astro.unige.ch/oda/api-clients/oda_api_wrapper
Author: Carlo Ferrigno
Author-email: carlo.ferrigno@unige.ch
Requires-Python: >=3.8
License-File: LICENSE.rst
Requires-Dist: astropy
Requires-Dist: matplotlib
Requires-Dist: numpy
Requires-Dist: oda-api
Requires-Dist: requests
Requires-Dist: astroquery
Requires-Dist: nlopt
Requires-Dist: autologging
Requires-Dist: PyYAML
Requires-Dist: pymosaic-fits
Requires-Dist: pluggy >=1.5.0
